arion/__init__.py
arion-0.0.0.dist-info/METADATA
arion-0.0.0.dist-info/WHEEL
arion-0.0.0.dist-info/top_level.txt
arion-0.0.0.dist-info/RECORD
