Metadata-Version: 2.1
Name: arion
Version: 0.0.0
Summary: Coming soon
